{
    "id":  "gruvbox-retro",
    "name":  "Gruvbox Retro",
    "configOverrides":  {
                            "bar.modules.paddingColor":  "#3c3836",
                            "bar.modules.radius":  18,
                            "bar.radius":  34,
                            "bar.merged":  true
                        },
    "configOverridesDark":  {
                                "bar.modules.paddingColor":  "#3c3836",
                                "bar.modules.radius":  18,
                                "bar.radius":  34,
                                "bar.merged":  true
                            },
    "configOverridesLight":  {
                                 "bar.modules.paddingColor":  "#d8c99d",
                                 "bar.modules.radius":  18,
                                 "bar.radius":  34,
                                 "bar.merged":  true
                             },
    "appearanceOverrides":  {
                                "m3background":  "#1a1c1d",
                                "m3error":  "#ffb4ab",
                                "m3errorContainer":  "#93000a",
                                "m3inverseOnSurface":  "#303030",
                                "m3inversePrimary":  "#8f5f00",
                                "m3inverseSurface":  "#e7e7e7",
                                "m3onBackground":  "#f7fff8",
                                "m3onError":  "#690005",
                                "m3onErrorContainer":  "#ffdad6",
                                "m3onPrimary":  "#101410",
                                "m3onPrimaryContainer":  "#f7fff8",
                                "m3onSecondary":  "#101410",
                                "m3onSecondaryContainer":  "#f7fff8",
                                "m3onSurface":  "#f7fff8",
                                "m3onSurfaceVariant":  "#c5cbc6",
                                "m3onTertiary":  "#101410",
                                "m3onTertiaryContainer":  "#f7fff8",
                                "m3outline":  "#95a39a",
                                "m3outlineVariant":  "#45534a",
                                "m3primary":  "#fabd2f",
                                "m3primaryContainer":  "#78612b",
                                "m3scrim":  "#000000",
                                "m3secondary":  "#b8bb26",
                                "m3secondaryContainer":  "#5f6027",
                                "m3shadow":  "#000000",
                                "m3sourceColor":  "#fabd2f",
                                "m3surface":  "#1a1c1d",
                                "m3surfaceBright":  "#424242",
                                "m3surfaceContainer":  "#282828",
                                "m3surfaceContainerHigh":  "#3c3836",
                                "m3surfaceContainerHighest":  "#4c4846",
                                "m3surfaceContainerLow":  "#222323",
                                "m3surfaceContainerLowest":  "#141617",
                                "m3surfaceDim":  "#171819",
                                "m3surfaceTint":  "#fabd2f",
                                "m3surfaceVariant":  "#32302f",
                                "m3tertiary":  "#fe8019",
                                "m3tertiaryContainer":  "#794922"
                            },
    "appearanceOverridesDark":  {
                                    "m3background":  "#1a1c1d",
                                    "m3error":  "#ffb4ab",
                                    "m3errorContainer":  "#93000a",
                                    "m3inverseOnSurface":  "#303030",
                                    "m3inversePrimary":  "#8f5f00",
                                    "m3inverseSurface":  "#e7e7e7",
                                    "m3onBackground":  "#f7fff8",
                                    "m3onError":  "#690005",
                                    "m3onErrorContainer":  "#ffdad6",
                                    "m3onPrimary":  "#101410",
                                    "m3onPrimaryContainer":  "#f7fff8",
                                    "m3onSecondary":  "#101410",
                                    "m3onSecondaryContainer":  "#f7fff8",
                                    "m3onSurface":  "#f7fff8",
                                    "m3onSurfaceVariant":  "#c5cbc6",
                                    "m3onTertiary":  "#101410",
                                    "m3onTertiaryContainer":  "#f7fff8",
                                    "m3outline":  "#95a39a",
                                    "m3outlineVariant":  "#45534a",
                                    "m3primary":  "#fabd2f",
                                    "m3primaryContainer":  "#78612b",
                                    "m3scrim":  "#000000",
                                    "m3secondary":  "#b8bb26",
                                    "m3secondaryContainer":  "#5f6027",
                                    "m3shadow":  "#000000",
                                    "m3sourceColor":  "#fabd2f",
                                    "m3surface":  "#1a1c1d",
                                    "m3surfaceBright":  "#424242",
                                    "m3surfaceContainer":  "#282828",
                                    "m3surfaceContainerHigh":  "#3c3836",
                                    "m3surfaceContainerHighest":  "#4c4846",
                                    "m3surfaceContainerLow":  "#222323",
                                    "m3surfaceContainerLowest":  "#141617",
                                    "m3surfaceDim":  "#171819",
                                    "m3surfaceTint":  "#fabd2f",
                                    "m3surfaceVariant":  "#32302f",
                                    "m3tertiary":  "#fe8019",
                                    "m3tertiaryContainer":  "#794922"
                                },
    "appearanceOverridesLight":  {
                                     "m3background":  "#fbf1c7",
                                     "m3error":  "#ba1a1a",
                                     "m3errorContainer":  "#ffdad6",
                                     "m3inverseOnSurface":  "#f1f1f1",
                                     "m3inversePrimary":  "#fabd2f",
                                     "m3inverseSurface":  "#303030",
                                     "m3onBackground":  "#101410",
                                     "m3onError":  "#ffffff",
                                     "m3onErrorContainer":  "#410002",
                                     "m3onPrimary":  "#f7fff8",
                                     "m3onPrimaryContainer":  "#101410",
                                     "m3onSecondary":  "#f7fff8",
                                     "m3onSecondaryContainer":  "#101410",
                                     "m3onSurface":  "#101410",
                                     "m3onSurfaceVariant":  "#424236",
                                     "m3onTertiary":  "#f7fff8",
                                     "m3onTertiaryContainer":  "#101410",
                                     "m3outline":  "#65736b",
                                     "m3outlineVariant":  "#bbc7bd",
                                     "m3primary":  "#8f5f00",
                                     "m3primaryContainer":  "#dbccad",
                                     "m3scrim":  "#000000",
                                     "m3secondary":  "#6c782e",
                                     "m3secondaryContainer":  "#d0d4bc",
                                     "m3shadow":  "#000000",
                                     "m3sourceColor":  "#8f5f00",
                                     "m3surface":  "#fbf1c7",
                                     "m3surfaceBright":  "#f4eac8",
                                     "m3surfaceContainer":  "#f2e5bc",
                                     "m3surfaceContainerHigh":  "#d8c99d",
                                     "m3surfaceContainerHighest":  "#cfc197",
                                     "m3surfaceContainerLow":  "#f6eac1",
                                     "m3surfaceContainerLowest":  "#fdf7e0",
                                     "m3surfaceDim":  "#eee5bd",
                                     "m3surfaceTint":  "#8f5f00",
                                     "m3surfaceVariant":  "#e2d4a9",
                                     "m3tertiary":  "#af3a03",
                                     "m3tertiaryContainer":  "#e5c0ae"
                                 }
}